aiohttp_devtools/__init__.py
aiohttp_devtools/__main__.py
aiohttp_devtools/cli.py
aiohttp_devtools/exceptions.py
aiohttp_devtools/logs.py
aiohttp_devtools/runserver/__init__.py
aiohttp_devtools/runserver/config.py
aiohttp_devtools/runserver/livereload.js
aiohttp_devtools/runserver/log_handlers.py
aiohttp_devtools/runserver/main.py
aiohttp_devtools/runserver/serve.py
aiohttp_devtools/runserver/utils.py
aiohttp_devtools/runserver/watch.py
aiohttp_devtools-1.1.2.dist-info/LICENSE
aiohttp_devtools-1.1.2.dist-info/METADATA
aiohttp_devtools-1.1.2.dist-info/WHEEL
aiohttp_devtools-1.1.2.dist-info/entry_points.txt
aiohttp_devtools-1.1.2.dist-info/top_level.txt
aiohttp_devtools-1.1.2.dist-info/zip-safe
aiohttp_devtools-1.1.2.dist-info/RECORD
