Metadata-Version: 2.1
Name: aiohttp-devtools
Version: 1.1.2
Summary: Dev tools for aiohttp
Home-page: https://github.com/aio-libs/aiohttp-devtools
Author: Samuel Colvin
Author-email: s@muelcolvin.com
License: MIT
Project-URL: CI: AppVeyor, https://ci.appveyor.com/project/aio-libs/aiohttp-devtools
Project-URL: CI: Travis, https://travis-ci.com/aio-libs/aiohttp-devtools
Project-URL: Coverage: codecov, https://codecov.io/github/aio-libs/aiohttp-devtools
Project-URL: GitHub: issues, https://github.com/aio-libs/aiohttp-devtools/issues
Project-URL: GitHub: repo, https://github.com/aio-libs/aiohttp-devtools
Classifier: Development Status :: 5 - Production/Stable
Classifier: Environment :: Console
Classifier: Programming Language :: Python
Classifier: Programming Language :: Python :: 3
Classifier: Programming Language :: Python :: 3.8
Classifier: Programming Language :: Python :: 3.9
Classifier: Programming Language :: Python :: 3.10
Classifier: Programming Language :: Python :: 3.11
Classifier: Intended Audience :: Developers
Classifier: Intended Audience :: Information Technology
Classifier: Intended Audience :: System Administrators
Classifier: License :: OSI Approved :: MIT License
Classifier: Operating System :: Microsoft :: Windows
Classifier: Operating System :: POSIX :: Linux
Classifier: Operating System :: Unix
Classifier: Environment :: MacOS X
Classifier: Topic :: Software Development :: Libraries :: Python Modules
Classifier: Topic :: Internet
Classifier: Framework :: AsyncIO
Classifier: Framework :: aiohttp
Requires-Python: >=3.8
License-File: LICENSE
Requires-Dist: aiohttp>=3.9
Requires-Dist: click>=6.6
Requires-Dist: devtools>=0.6
Requires-Dist: Pygments>=2.2.0
Requires-Dist: watchfiles>=0.10
